LICENSE
README.md
setup.py
discwrappy/Gateway.py
discwrappy/Objects.py
discwrappy/__init__.py
discwrappy/utils.py
discwrappy.egg-info/PKG-INFO
discwrappy.egg-info/SOURCES.txt
discwrappy.egg-info/dependency_links.txt
discwrappy.egg-info/requires.txt
discwrappy.egg-info/top_level.txt