Metadata-Version: 2.1
Name: discwrappy
Version: 0.5
Summary: A Python wrapper for the Discord API
Home-page: https://github.com/JeffTheModder/DiscWrappy
Download-URL: https://github.com/JeffTheModder/DiscWrappy/archive/refs/tags/v_0.5.tar.gz
Author: Jeff Morris
Author-email: jeffreyjr.morris@gmail.com
Keywords: Discord,API,wrapper,python,library
Classifier: Development Status :: 3 - Alpha
Classifier: Intended Audience :: Developers
Classifier: License :: OSI Approved :: GNU General Public License v3 (GPLv3)
Classifier: Topic :: Software Development :: Libraries
Classifier: Programming Language :: Python
License-File: LICENSE
